rsidatasciencetools/__init__.py
rsidatasciencetools/add.py
rsidatasciencetools/utils.py
rsidatasciencetools/apiutil/Dockerfile
rsidatasciencetools/apiutil/__init__.py
rsidatasciencetools/apiutil/api.py
rsidatasciencetools/apiutil/docker-compose.yml
rsidatasciencetools/apiutil/python_schemas.py
rsidatasciencetools/apiutil/requirements.txt
rsidatasciencetools/apiutil/matchingapi/README.md
rsidatasciencetools/apiutil/matchingapi/__init__.py
rsidatasciencetools/apiutil/matchingapi/app.py
rsidatasciencetools/apiutil/matchingapi/schemas.py
rsidatasciencetools/apiutil/matchingapi/docker/.dockerignore
rsidatasciencetools/apiutil/matchingapi/docker/Dockerfile.base
rsidatasciencetools/apiutil/matchingapi/docker/Dockerfile.final
rsidatasciencetools/apiutil/matchingapi/docker/Dockerfile.middle
rsidatasciencetools/apiutil/matchingapi/docker/README.md
rsidatasciencetools/apiutil/matchingapi/docker/bash_aliases
rsidatasciencetools/apiutil/matchingapi/docker/docker-compose.base.yml
rsidatasciencetools/apiutil/matchingapi/docker/docker-compose.middle.yml
rsidatasciencetools/apiutil/matchingapi/docker/docker-compose.override.yml
rsidatasciencetools/apiutil/matchingapi/docker/docker-compose.yml
rsidatasciencetools/apiutil/matchingapi/docker/prep_pkgs_for_docker.sh
rsidatasciencetools/apiutil/matchingapi/docker/prep_pkgs_for_docker_for_ga.sh
rsidatasciencetools/apiutil/matchingapi/docker/push_base_docker_to_acr.sh
rsidatasciencetools/apiutil/matchingapi/docker/run_docker.sh
rsidatasciencetools/apiutil/matchingapi/docker/supervisord.conf
rsidatasciencetools/apiutil/matchingapi/tests/default_matching_config.yml
rsidatasciencetools/apiutil/matchingapi/tests/test_post_config.txt
rsidatasciencetools/azureutils/README.md
rsidatasciencetools/azureutils/__init__.py
rsidatasciencetools/azureutils/az_blobdata_io.py
rsidatasciencetools/azureutils/az_data_io.py
rsidatasciencetools/azureutils/az_logging.py
rsidatasciencetools/azureutils/azure_get_plat_config.py
rsidatasciencetools-0.0.5.dist-info/METADATA
rsidatasciencetools-0.0.5.dist-info/WHEEL
rsidatasciencetools-0.0.5.dist-info/licenses/LICENSE
rsidatasciencetools-0.0.5.dist-info/RECORD
