Metadata-Version: 2.1
Name: rsidatasciencetools
Version: 0.0.5
Summary: RSI Data Science Tools package
Project-URL: Homepage, https://github.com/revenue-solutions-inc/DataScienceTools
Project-URL: Bug Tracker, https://github.com/revenue-solutions-inc/DataScienceTools/issues
Author-email: Gurinder Pal Singh <gpsingh@rsimail.com>
License-File: LICENSE
Classifier: License :: OSI Approved :: MIT License
Classifier: Operating System :: OS Independent
Classifier: Programming Language :: Python :: 3
Requires-Python: >=3.7
